{"cameraMode":{"drawMode":0,"name":"Shaded","section":"Shading Mode"},"sceneLighting":true,"audioPlay":false,"sceneViewState":{"m_AlwaysRefresh":false,"showFog":true,"showSkybox":true,"showFlares":true,"showImageEffects":true,"showParticleSystems":true,"showVisualEffectGraphs":true,"m_FxEnabled":true},"in2DMode":false,"pivot":{"x":752.948974609375,"y":403.5,"z":0.0},"rotation":{"x":0.10516376793384552,"y":0.5277460217475891,"z":-0.0660587027668953,"w":0.840387225151062},"size":923.2540893554688,"orthographic":false}