{"cameraMode":{"drawMode":0,"name":"Shaded","section":"Shading Mode"},"sceneLighting":true,"audioPlay":false,"sceneViewState":{"showFog":true,"showMaterialUpdate":false,"showSkybox":true,"showFlares":true,"showImageEffects":true,"showParticleSystems":true},"in2DMode":false,"pivot":{"x":-14.454421043395996,"y":11.477898597717286,"z":-3.030874490737915},"rotation":{"x":-0.16579781472682954,"y":-0.6694106459617615,"z":0.15694789588451386,"w":-0.706996500492096},"size":0.025980759412050248,"orthographic":false}